protectedclasses/__init__.py
protectedclasses/tests/__init__.py
protectedclasses/tests/test_1984.py
protectedclasses/tests/test_protected.py
protectedclasses-1.0.0.dist-info/LICENSE.txt
protectedclasses-1.0.0.dist-info/METADATA
protectedclasses-1.0.0.dist-info/WHEEL
protectedclasses-1.0.0.dist-info/top_level.txt
protectedclasses-1.0.0.dist-info/RECORD
