Metadata-Version: 2.1
Name: protectedclasses
Version: 1.0.0
Summary: Protected classes.
Author-email: Johannes <johannes-programming@mailfence.com>
License: The MIT License (MIT)
Project-URL: Documentation, https://pypi.org/project/protectedclasses
Project-URL: Download, https://pypi.org/project/protectedclasses/#files
Project-URL: Source, https://github.com/johannes-programming/protectedclasses
Classifier: Development Status :: 5 - Production/Stable
Classifier: License :: OSI Approved :: MIT License
Classifier: Programming Language :: Python
Classifier: Programming Language :: Python :: 3
Classifier: Programming Language :: Python :: 3 :: Only
Requires-Python: >=3.8
License-File: LICENSE.txt
